scrikit/__init__.py
scrikit/ansi.py
scrikit/log.py
scrikit/menu.py
scrikit/script.py
scrikit/table.py
scrikit/theme.py
scrikit/tree.py
scrikit-1.0.0.dist-info/METADATA
scrikit-1.0.0.dist-info/WHEEL
scrikit-1.0.0.dist-info/licenses/LICENSE
scrikit-1.0.0.dist-info/RECORD
