Metadata-Version: 2.4
Name: scrikit
Version: 1.0.0
Summary: A simple Script Kit with essential tools for Python developers.
Project-URL: Homepage, https://github.com/coryavra/scrikit
Project-URL: Issues, https://github.com/coryavra/scrikit/issues
Author-email: Cory Avra <coryavra@icloud.com>
License-Expression: MIT
License-File: LICENSE
Classifier: License :: OSI Approved :: MIT License
Classifier: Operating System :: OS Independent
Classifier: Programming Language :: Python :: 3
Requires-Python: >=3.8
